[
  {
    "title": "Ultraboost 5X Shoes",
    "price": "$180"
  },
  {
    "title": "Ultraboost 5X Shoes",
    "price": "$180"
  },
  {
    "title": "Ultraboost 5X Shoes",
    "price": "$180"
  },
  {
    "title": "Ultraboost 5X Shoes",
    "price": "$180"
  },
  {
    "title": "Ultraboost 5X Shoes",
    "price": "$180"
  },
  {
    "title": "adidas by Stella McCartney Ultraboost 5 Shoes",
    "price": "$250"
  },
  {
    "title": "Y-3 Ultraboost 5",
    "price": "No price available"
  },
  {
    "title": "Ultraboost 5X Shoes",
    "price": "No price available"
  },
  {
    "title": "Marvel Graphic Tee",
    "price": "No price available"
  },
  {
    "title": "Adicolor Knit Skirt",
    "price": "No price available"
  },
  {
    "title": "Samba OG Shoes",
    "price": "No price available"
  },
  {
    "title": "Gazelle Indoor Shoes",
    "price": "No price available"
  },
  {
    "title": "Puig Samba Shoes",
    "price": "$100"
  },
  {
    "title": "Gazelle Indoor Shoes",
    "price": "$120"
  },
  {
    "title": "Superlite 3 Hat",
    "price": "$26"
  },
  {
    "title": "Trefoil Essentials Shorts",
    "price": "$40"
  },
  {
    "title": "Adicolor Pleather Shorts",
    "price": "$70"
  },
  {
    "title": "Adicolor 3-Stripes Loose French Terry Wide Leg Pants",
    "price": "$85"
  },
  {
    "title": "Premium Essentials Denim Track Top",
    "price": "$100"
  },
  {
    "title": "Athletic Cushioned Crew Socks 6 Pairs",
    "price": "$22"
  },
  {
    "title": "Handball Spezial Shoes",
    "price": "$110"
  },
  {
    "title": "Samba OG Shoes",
    "price": "$120"
  },
  {
    "title": "Samba OG Shoes",
    "price": "$100"
  },
  {
    "title": "Samba OG Shoes",
    "price": "$100"
  },
  {
    "title": "SL 72 OG Shoes",
    "price": "No price available"
  },
  {
    "title": "Runfalcon 5 Running Shoes",
    "price": "No price available"
  },
  {
    "title": "Samba OG Shoes",
    "price": "No price available"
  },
  {
    "title": "Gazelle Indoor Shoes",
    "price": "$120"
  },
  {
    "title": "Campus 00s Shoes",
    "price": "$90"
  },
  {
    "title": "Samba XLG Shoes",
    "price": "$110"
  },
  {
    "title": "Campus 00s Elastic Laces Shoes Kids",
    "price": "$70"
  },
  {
    "title": "Racer TR23 Shoes Kids",
    "price": "$55"
  },
  {
    "title": "Ultrarun 5 Shoes Kids",
    "price": "$55"
  },
  {
    "title": "Gazelle Indoor Shoes",
    "price": "$120"
  },
  {
    "title": "Ultrarun 5 Shoes Kids",
    "price": "$55"
  },
  {
    "title": "Ultrarun 5 Shoes Kids",
    "price": "$60"
  },
  {
    "title": "Y-3 Gazelle",
    "price": "$350"
  },
  {
    "title": "Gazelle Shoes Kids",
    "price": "$70"
  },
  {
    "title": "Gazelle Indoor Shoes",
    "price": "$120"
  },
  {
    "title": "SL 72 RS Shoes Kids",
    "price": "No price available"
  },
  {
    "title": "Samba XLG Shoes",
    "price": "No price available"
  },
  {
    "title": "Country Japan Shoes",
    "price": "No price available"
  },
  {
    "title": "Runfalcon 5 Running Shoes",
    "price": "No price available"
  },
  {
    "title": "Handball Spezial Shoes Kids",
    "price": "No price available"
  },
  {
    "title": "Crazy Mad IIInfinity Shoes",
    "price": "No price available"
  },
  {
    "title": "Gazelle Comfort Closure Elastic Laces Shoes Kids",
    "price": "No price available"
  },
  {
    "title": "ULTRABOOST 1.0 SHOES",
    "price": "No price available"
  },
  {
    "title": "Superstar Shoes",
    "price": "No price available"
  }
]